sheetwork/__init__.py
sheetwork/core/__init__.py
sheetwork/core/_version.py
sheetwork/core/adapters/__init__.py
sheetwork/core/adapters/base/__init__.py
sheetwork/core/adapters/base/connection.py
sheetwork/core/adapters/base/impl.py
sheetwork/core/adapters/connection.py
sheetwork/core/adapters/factory.py
sheetwork/core/adapters/impl.py
sheetwork/core/cleaner.py
sheetwork/core/clients/__init__.py
sheetwork/core/clients/google.py
sheetwork/core/clients/system.py
sheetwork/core/config/__init__.py
sheetwork/core/config/config.py
sheetwork/core/config/profile.py
sheetwork/core/config/project.py
sheetwork/core/exceptions.py
sheetwork/core/flags.py
sheetwork/core/logger.py
sheetwork/core/main.py
sheetwork/core/sheetwork.py
sheetwork/core/task/__init__.py
sheetwork/core/task/init.py
sheetwork/core/ui/__init__.py
sheetwork/core/ui/colours.py
sheetwork/core/ui/printer.py
sheetwork/core/ui/traceback_manager.py
sheetwork/core/utils.py
sheetwork/core/yaml/__init__.py
sheetwork/core/yaml/yaml_helpers.py
sheetwork/core/yaml/yaml_schema.py
sheetwork-1.0.7.dist-info/entry_points.txt
sheetwork-1.0.7.dist-info/LICENSE
sheetwork-1.0.7.dist-info/WHEEL
sheetwork-1.0.7.dist-info/METADATA
sheetwork-1.0.7.dist-info/RECORD
