Metadata-Version: 2.1
Name: sheetwork
Version: 1.0.7
Summary: A handy CLI tool to ingest GoogleSheets into your database without writing a single line of code
Home-page: https://github.com/bastienboutonnet/sheetwork
License: MIT
Keywords: googlesheets,snowflake,cli,ingest,data engineering
Author: Bastien Boutonnet
Author-email: bastien.b1@gmail.com
Maintainer: Bastien Boutonnet
Maintainer-email: bastien.b1@gmail.com
Requires-Python: >=3.6.1,<4.0
Classifier: Development Status :: 3 - Alpha
Classifier: Intended Audience :: Developers
Classifier: License :: OSI Approved :: MIT License
Classifier: Programming Language :: Python :: 3
Classifier: Programming Language :: Python :: 3.6
Classifier: Programming Language :: Python :: 3.7
Classifier: Programming Language :: Python :: 3.8
Classifier: Programming Language :: Python :: 3.9
Classifier: Topic :: Software Development :: Build Tools
Provides-Extra: test
Requires-Dist: cerberus (>=1.3.2,<2.0.0)
Requires-Dist: colorama (>=0.4.3,<0.5.0)
Requires-Dist: gspread (>=3.6,<4.0)
Requires-Dist: inflection (>=0.5.1,<0.6.0)
Requires-Dist: luddite (>=1.0.1,<2.0.0)
Requires-Dist: oauth2client (>=4.1.3,<5.0.0)
Requires-Dist: packaging (>=20.4,<21.0)
Requires-Dist: pandas (>=1.1.5,<1.2.0)
Requires-Dist: pretty-errors (>=1.2.19,<2.0.0)
Requires-Dist: pyyaml (>=5.3.1,<6.0.0)
Requires-Dist: requests (<2.23.0)
Requires-Dist: retrying (>=1.3.3,<2.0.0)
Requires-Dist: snowflake-sqlalchemy (>=1,<2)
Requires-Dist: sqlalchemy (>=1.3.19,<2.0.0)
Project-URL: Documentation, https://bitpicky.gitbook.io/sheetwork/
Project-URL: Repository, https://github.com/bastienboutonnet/sheetwork
